zimran/cli/__init__.py
zimran/cli/sync_api_docs.py
zimran/config/__init__.py
zimran_config-1.2.0.dist-info/METADATA
zimran_config-1.2.0.dist-info/WHEEL
zimran_config-1.2.0.dist-info/entry_points.txt
zimran_config-1.2.0.dist-info/top_level.txt
zimran_config-1.2.0.dist-info/RECORD
