Metadata-Version: 2.4
Name: zimran-config
Version: 1.2.0
Summary: Pydantic based configuration for FastAPI services
Requires-Python: >=3.10
Requires-Dist: pydantic-settings==2.*
Dynamic: description
Dynamic: description-content-type
Dynamic: requires-dist
Dynamic: requires-python
Dynamic: summary
